djaodjin_multitier-0.3.1.dist-info/licenses/LICENSE.txt
multitier/__init__.py
multitier/compat.py
multitier/context_processors.py
multitier/finders.py
multitier/middleware.py
multitier/mixins.py
multitier/models.py
multitier/routers.py
multitier/settings.py
multitier/thread_locals.py
multitier/urlresolvers.py
multitier/urlresolvers_py3_django2.py
multitier/utils.py
multitier/loaders/__init__.py
multitier/loaders/django.py
multitier/loaders/jinja2.py
multitier/templatetags/__init__.py
multitier/templatetags/multitier_tags.py
djaodjin_multitier-0.3.1.dist-info/METADATA
djaodjin_multitier-0.3.1.dist-info/WHEEL
djaodjin_multitier-0.3.1.dist-info/top_level.txt
djaodjin_multitier-0.3.1.dist-info/RECORD
