Metadata-Version: 2.4
Name: djaodjin-multitier
Version: 0.3.1
Summary: Django application that implements shared tenancy
Author-email: The DjaoDjin Team <help@djaodjin.com>
Maintainer-email: The DjaoDjin Team <help@djaodjin.com>
License: BSD-2-Clause
Project-URL: repository, https://github.com/djaodjin/djaodjin-multitier
Project-URL: documentation, https://djaodjin-multitier.readthedocs.io/
Project-URL: changelog, https://github.com/djaodjin/djaodjin-multitier/changelog
Keywords: django,multitier,databases,routers
Classifier: Framework :: Django
Classifier: Environment :: Web Environment
Classifier: Programming Language :: Python
Classifier: License :: OSI Approved :: BSD License
Requires-Python: >=3.7
License-File: LICENSE.txt
Requires-Dist: Django>=1.11
Requires-Dist: djaodjin-deployutils>=0.5.23
Dynamic: license-file
